badwulf/__init__.py
badwulf/expdb.py
badwulf/rssh.py
badwulf/tools.py
badwulf/cli/__init__.py
badwulf/cli/clmanager.py
badwulf/cli/dbmanager.py
badwulf-0.1.27.dist-info/licenses/LICENSE
badwulf-0.1.27.dist-info/METADATA
badwulf-0.1.27.dist-info/WHEEL
badwulf-0.1.27.dist-info/top_level.txt
badwulf-0.1.27.dist-info/RECORD
