Metadata-Version: 2.4
Name: badwulf
Version: 0.1.27
Summary: Minimal manager for Beowulf clusters and scientific data
Author-email: "Kylie A. Bemis" <k.bemis@northeastern.edu>
License: Artistic License 2.0
Project-URL: Homepage, https://github.com/kuwisdelu/badwulf
Project-URL: Issues, https://github.com/kuwisdelu/badwulf/issues
Classifier: Development Status :: 3 - Alpha
Classifier: Programming Language :: Python :: 3
Classifier: Programming Language :: Python :: 3.10
Classifier: Programming Language :: Python :: 3.11
Classifier: Programming Language :: Python :: 3.12
Classifier: Programming Language :: Python :: 3.13
Classifier: License :: OSI Approved :: Artistic License
Classifier: Intended Audience :: Science/Research
Classifier: Operating System :: Unix
Requires-Python: >=3.10
License-File: LICENSE
Requires-Dist: tomli>=1.1.0; python_version < "3.11"
Provides-Extra: test
Requires-Dist: pytest; extra == "test"
Dynamic: license-file
